limipy/__init__.py
limipy-1.0.1.dist-info/METADATA
limipy-1.0.1.dist-info/WHEEL
limipy-1.0.1.dist-info/top_level.txt
limipy-1.0.1.dist-info/RECORD
