Metadata-Version: 2.4
Name: limipy
Version: 1.0.1
Summary: The LimiPlake Python Package- for students AND teachers.
Home-page: https://limiplake.com
Author: Anhad Jain
Author-email: anhad@limiplake.com
Classifier: Programming Language :: Python :: 3
Classifier: Intended Audience :: Education
Classifier: License :: OSI Approved :: MIT License
Classifier: Operating System :: OS Independent
Requires-Python: >=3.9
Dynamic: author
Dynamic: author-email
Dynamic: classifier
Dynamic: description
Dynamic: description-content-type
Dynamic: home-page
Dynamic: requires-python
Dynamic: summary
